pyIpnHeuristic/__init__.py
pyIpnHeuristic/artificialBeeColony.py
pyIpnHeuristic/differentialEvolution.py
pyIpnHeuristic/harmonySearch.py
pyIpnHeuristic/modifiedHarmonySearch.py
pyIpnHeuristic/particleSwarmOptimization.py
pyIpnHeuristic/benchmark/__init__.py
pyIpnHeuristic/benchmark/benchmark.py
pyIpnHeuristic/benchmark/constants.py
pyIpnHeuristic-2.0.0.dist-info/LICENSE
pyIpnHeuristic-2.0.0.dist-info/METADATA
pyIpnHeuristic-2.0.0.dist-info/WHEEL
pyIpnHeuristic-2.0.0.dist-info/top_level.txt
pyIpnHeuristic-2.0.0.dist-info/RECORD
