Metadata-Version: 2.1
Name: pyIpnHeuristic
Version: 2.0.0
Summary: pyIpnHeuristic is a pure Python implementation of some heuristic algorithms
Home-page: https://github.com/niortizva/pyIpnHeuristic
Author: Nicolas Ortiz
Author-email: nortizv2100@alumno.ipn.com
Maintainer: Nicolas Ortiz
Maintainer-email: nortizv2100@alumno.ipn.com
License: MIT
Classifier: Programming Language :: Python :: 3
Classifier: License :: OSI Approved :: MIT License
Classifier: Topic :: Scientific/Engineering :: Artificial Intelligence
License-File: LICENSE
